README.md
setup.py
SePyrability.egg-info/PKG-INFO
SePyrability.egg-info/SOURCES.txt
SePyrability.egg-info/dependency_links.txt
SePyrability.egg-info/requires.txt
SePyrability.egg-info/top_level.txt
sepyrability/__init__.py
sepyrability/distance.py
sepyrability/separability.py