Metadata-Version: 2.1
Name: SePyrability
Version: 0.0.1
Summary: Python implementation of the multiscale separability metric.
Home-page: https://github.com/jrjoaorenato/SePYrability
Author: João Renato Ribeiro manesco
Author-email: joaorenatorm@gmail.com
License: MIT
Download-URL: https://github.com/jrjoaorenato/SePYrability/archive/v0.0.1.tar.gz
Keywords: Separability,Metric
Platform: UNKNOWN
Classifier: Development Status :: 3 - Alpha
Classifier: Intended Audience :: Developers
Classifier: Topic :: Software Development :: Build Tools
Classifier: License :: OSI Approved :: MIT License
Classifier: Programming Language :: Python :: 3
